hashwd/__init__.py
hashwd/__main__.py
hashwd/dictionary.py
hashwd/hashwd.py
hashwd/pass_defaults.py
hashwd-0.5.1.dist-info/entry_points.txt
hashwd-0.5.1.dist-info/LICENSE
hashwd-0.5.1.dist-info/METADATA
hashwd-0.5.1.dist-info/WHEEL
hashwd-0.5.1.dist-info/RECORD
