Metadata-Version: 2.1
Name: hashwd
Version: 0.5.1
Summary: Quickly generate a strong, random password using common words
Home-page: https://pypi.org/project/hashwd
License: GPL-3.0
Keywords: password,generator,xkcd
Author: Jordan Langland
Author-email: root@gnom.me
Requires-Python: >=3.6,<4.0
Classifier: License :: OSI Approved :: GNU General Public License v3 (GPLv3)
Classifier: Programming Language :: Python :: 3
Classifier: Programming Language :: Python :: 3.6
Classifier: Programming Language :: Python :: 3.7
Classifier: Programming Language :: Python :: 3.8
Classifier: Programming Language :: Python :: 3.9
Classifier: Programming Language :: Python :: 3.10
Classifier: Programming Language :: Python :: 3.11
Requires-Dist: argparse (>=1.4,<2.0)
Requires-Dist: pyperclip (>=1.8,<2.0)
Requires-Dist: requests (>=2.24,<3.0)
Project-URL: Repository, https://github.com/stellarsu/hashwd
